{
  "generatedAt": "2026-07-21T01:10:20.930844+00:00",
  "aiInsightsUpdatedAt": "2026-07-15T07:59:42.742159+00:00",
  "usdTryRate": 47.18339920043945,
  "netWorth": {
    "total": 88613.43578677687,
    "categories": [
      {
        "id": "us-stocks",
        "name": "ABD Hisse Portföyü",
        "subtitle": "ABD Hisse",
        "value": 19036.583731999996,
        "weightPct": 21.5
      },
      {
        "id": "real-estate",
        "name": "Gayrimenkul",
        "subtitle": "Uzun vadeli çekirdek",
        "value": 0,
        "weightPct": 0.0
      },
      {
        "id": "bist",
        "name": "Borsa İstanbul",
        "subtitle": "Bist Hisse",
        "value": 18753.71581943504,
        "weightPct": 21.2
      },
      {
        "id": "crypto-spot",
        "name": "Kripto SPOT",
        "subtitle": "Spot kripto varlıklar",
        "value": 8443.766981849689,
        "weightPct": 9.5
      },
      {
        "id": "cash",
        "name": "Nakit",
        "subtitle": "USD / USDT / TRY",
        "value": 17086.03838474813,
        "weightPct": 19.3
      },
      {
        "id": "gold",
        "name": "Altın",
        "subtitle": "Değer saklama / hedge",
        "value": 19793.33086874401,
        "weightPct": 22.3
      },
      {
        "id": "btc-futures",
        "name": "Bitcoin Futures",
        "subtitle": "Trade - Kaldıraçlı İşlemler",
        "value": 5500,
        "weightPct": 6.2
      }
    ]
  },
  "stockPortfolio": {
    "total": 63320.104918032855,
    "positionCount": 18,
    "holdings": [
      {
        "ticker": "CASH",
        "name": "Nakit (USD / USDT / TRY)",
        "subtitle": "USD / USDT / TRY",
        "assetClass": "Nakit",
        "shares": null,
        "price": null,
        "value": 17086.03838474813,
        "weightPct": 27.0
      },
      {
        "ticker": "VOO",
        "name": "S&P 500 Endeks fonu",
        "assetClass": "ETF",
        "shares": 11.39,
        "price": 682.21,
        "currency": "USD",
        "value": 7770.371900000001,
        "valueTRY": 366632.5592935772,
        "avgCost": 601.99,
        "costTotalNative": 6856.6661,
        "returnNative": 913.7058000000006,
        "returnPct": 13.325802754198591,
        "inflationAltTRY": 330134.7996343131,
        "logoUrl": "https://images.financialmodelingprep.com/symbol/VOO.png",
        "weightPct": 12.3
      },
      {
        "ticker": "GARAN.IS",
        "name": "Garanti BBVA",
        "assetClass": "BIST",
        "shares": 2599,
        "price": 126.8,
        "currency": "TRY",
        "value": 6984.515859063639,
        "valueTRY": 329553.2,
        "avgCost": 137.51719122739516,
        "costTotalNative": 357407.18,
        "returnNative": -27853.97999999998,
        "returnPct": -7.793346513072286,
        "inflationAltTRY": 384458.91161449807,
        "logoUrl": null,
        "weightPct": 11.0
      },
      {
        "ticker": "ISCTR.IS",
        "name": "İş Bankası",
        "assetClass": "BIST",
        "shares": 19200,
        "price": 13.68,
        "currency": "TRY",
        "value": 5566.703638375289,
        "valueTRY": 262656.0,
        "avgCost": 15.174118749999998,
        "costTotalNative": 291343.07999999996,
        "returnNative": -28687.079999999958,
        "returnPct": -9.846494380439708,
        "inflationAltTRY": 317365.2104635624,
        "logoUrl": null,
        "weightPct": 8.8
      },
      {
        "ticker": "BTC-USD",
        "name": "Bitcoin",
        "assetClass": "Kripto",
        "shares": 0.06276876,
        "price": 65601.5938,
        "currency": "USD",
        "value": 4117.730696849689,
        "valueTRY": 194288.5312693626,
        "avgCost": 74336.0,
        "costTotalNative": 4665.978543360001,
        "returnNative": -548.2478465103122,
        "returnPct": -11.749900721050366,
        "inflationAltTRY": 224794.44269152478,
        "logoUrl": null,
        "weightPct": 6.5
      },
      {
        "ticker": "MSFT",
        "name": "Microsoft",
        "assetClass": "ABD Hisse",
        "shares": 8.7,
        "price": 402.29,
        "currency": "USD",
        "value": 3499.923,
        "valueTRY": 165138.26407979964,
        "avgCost": 408.26,
        "costTotalNative": 3551.8619999999996,
        "returnNative": -51.93899999999985,
        "returnPct": -1.4623034340861207,
        "inflationAltTRY": 171015.07242692332,
        "logoUrl": "https://images.financialmodelingprep.com/symbol/MSFT.png",
        "weightPct": 5.5
      },
      {
        "ticker": "SCHD",
        "name": "US Dividend Equity ETF",
        "assetClass": "ETF",
        "shares": 101,
        "price": 32.75,
        "currency": "USD",
        "value": 3307.75,
        "valueTRY": 156070.8887052536,
        "avgCost": 28.58,
        "costTotalNative": 2886.58,
        "returnNative": 421.1700000000001,
        "returnPct": 14.590622813156063,
        "inflationAltTRY": 138983.07078543835,
        "logoUrl": "https://images.financialmodelingprep.com/symbol/SCHD.png",
        "weightPct": 5.2
      },
      {
        "ticker": "ETH-USD",
        "name": "Ethereum",
        "assetClass": "Kripto",
        "shares": 1.4555,
        "price": 1916.87,
        "currency": "USD",
        "value": 2790.004285,
        "valueTRY": 131641.88595009164,
        "avgCost": 2288.0,
        "costTotalNative": 3330.184,
        "returnNative": -540.1797150000002,
        "returnPct": -16.220716783216794,
        "inflationAltTRY": 164759.94114138355,
        "logoUrl": null,
        "weightPct": 4.4
      },
      {
        "ticker": "JEPQ",
        "name": "JPMorgan Nasdaq Equity Premium Income ETF",
        "assetClass": "ETF",
        "shares": 37.44,
        "price": 58.59,
        "currency": "USD",
        "value": 2193.6096,
        "valueTRY": 103501.9574467163,
        "avgCost": 56.43,
        "costTotalNative": 2112.7392,
        "returnNative": 80.87039999999979,
        "returnPct": 3.8277511961722466,
        "inflationAltTRY": 101724.17940426744,
        "logoUrl": "https://images.financialmodelingprep.com/symbol/JEPQ.png",
        "weightPct": 3.5
      },
      {
        "ticker": "THYAO.IS",
        "name": "THY",
        "assetClass": "BIST",
        "shares": 310,
        "price": 329.5,
        "currency": "TRY",
        "value": 2164.8503865963235,
        "valueTRY": 102145.00000000001,
        "avgCost": 298.8,
        "costTotalNative": 92628.0,
        "returnNative": 9517.0,
        "returnPct": 10.274431057563582,
        "inflationAltTRY": 102282.00890596372,
        "logoUrl": null,
        "weightPct": 3.4
      },
      {
        "ticker": "FROTO.IS",
        "name": "Ford Otosan",
        "assetClass": "BIST",
        "shares": 1192,
        "price": 83.6,
        "currency": "TRY",
        "value": 2111.997051689143,
        "valueTRY": 99651.2,
        "avgCost": 106.0,
        "costTotalNative": 126352.0,
        "returnNative": -26700.800000000003,
        "returnPct": -21.13207547169812,
        "inflationAltTRY": 137665.98322732002,
        "logoUrl": null,
        "weightPct": 3.3
      },
      {
        "ticker": "PETKM.IS",
        "name": "Petkim Petrokimya Holding",
        "assetClass": "BIST",
        "shares": 4339,
        "price": 20.94,
        "currency": "TRY",
        "value": 1925.6488837106456,
        "valueTRY": 90858.66,
        "avgCost": 20.16,
        "costTotalNative": 87474.24,
        "returnNative": 3384.4199999999983,
        "returnPct": 3.8690476190476275,
        "inflationAltTRY": 92295.25551270985,
        "logoUrl": null,
        "weightPct": 3.0
      },
      {
        "ticker": "SPGI",
        "name": "S&P Global",
        "assetClass": "ABD Hisse",
        "shares": 2.9,
        "price": 448.35,
        "currency": "USD",
        "value": 1300.215,
        "valueTRY": 61348.56339139938,
        "avgCost": 434.02,
        "costTotalNative": 1258.658,
        "returnNative": 41.557000000000016,
        "returnPct": 3.301691166305698,
        "inflationAltTRY": 66866.58799582128,
        "logoUrl": "https://images.financialmodelingprep.com/symbol/SPGI.png",
        "weightPct": 2.1
      },
      {
        "ticker": "SOL-USD",
        "name": "Solana",
        "assetClass": "Kripto",
        "shares": 9.656,
        "price": 78.17,
        "currency": "USD",
        "value": 754.80952,
        "valueTRY": 35614.47890245209,
        "avgCost": 83.0,
        "costTotalNative": 801.4480000000001,
        "returnNative": -46.63848000000007,
        "returnPct": -5.81927710843374,
        "inflationAltTRY": 43342.943232651596,
        "logoUrl": null,
        "weightPct": 1.2
      },
      {
        "ticker": "ASTS",
        "name": "AST SpaceMobile",
        "assetClass": "ABD Hisse",
        "shares": 9.44,
        "price": 57.42,
        "currency": "USD",
        "value": 542.0448,
        "valueTRY": 25575.516182922365,
        "avgCost": 74.17,
        "costTotalNative": 700.1648,
        "returnNative": -158.12,
        "returnPct": -22.583254685182684,
        "inflationAltTRY": 33394.74788261923,
        "logoUrl": "https://images.financialmodelingprep.com/symbol/ASTS.png",
        "weightPct": 0.9
      },
      {
        "ticker": "AVAX-USD",
        "name": "Avax",
        "assetClass": "Kripto",
        "shares": 87.614,
        "price": 6.62,
        "currency": "USD",
        "value": 580.00468,
        "valueTRY": 27366.59235456314,
        "avgCost": 10.1,
        "costTotalNative": 884.9014,
        "returnNative": -304.89671999999996,
        "returnPct": -34.45544554455445,
        "inflationAltTRY": 48099.82122494708,
        "logoUrl": null,
        "weightPct": 0.9
      },
      {
        "ticker": "AVGO",
        "name": "Broadcom Inc.",
        "assetClass": "ABD Hisse",
        "shares": 1.1177,
        "price": 378.16,
        "currency": "USD",
        "value": 422.669432,
        "valueTRY": 19942.980539878998,
        "avgCost": 357.85,
        "costTotalNative": 399.968945,
        "returnNative": 22.700486999999953,
        "returnPct": 5.675562386474775,
        "inflationAltTRY": 19147.213959234534,
        "logoUrl": "https://images.financialmodelingprep.com/symbol/AVGO.png",
        "weightPct": 0.7
      },
      {
        "ticker": "HYPE-USD",
        "name": "Hyperliquid",
        "assetClass": "Kripto",
        "shares": 3.22,
        "price": 62.49,
        "currency": "USD",
        "value": 201.2178,
        "valueTRY": 9494.139783634186,
        "avgCost": 62.0,
        "costTotalNative": 199.64000000000001,
        "returnNative": 1.5777999999999963,
        "returnPct": 0.790322580645153,
        "inflationAltTRY": 9614.464549928645,
        "logoUrl": null,
        "weightPct": 0.3
      }
    ]
  },
  "assetClasses": [
    {
      "name": "BIST",
      "value": 18753.71581943504,
      "weightPct": 29.6
    },
    {
      "name": "Nakit",
      "value": 17086.03838474813,
      "weightPct": 27.0
    },
    {
      "name": "ETF",
      "value": 13271.731500000002,
      "weightPct": 21.0
    },
    {
      "name": "Kripto",
      "value": 8443.766981849689,
      "weightPct": 13.3
    },
    {
      "name": "ABD Hisse",
      "value": 5764.852231999999,
      "weightPct": 9.1
    }
  ],
  "momentum": {
    "index": [
      {
        "ticker": "GSPC",
        "name": "S&P 500",
        "group": "index",
        "d50": -0.3102099019356652,
        "d200": 6.469402782358524,
        "w50": 7.398185653253431,
        "w100": 16.221649638701585,
        "w200": 35.9668441376658,
        "status": "—"
      },
      {
        "ticker": "NDX",
        "name": "Nasdaq 100",
        "group": "index",
        "d50": -3.1967315098882176,
        "d200": 8.531513922711763,
        "w50": 9.918913852793798,
        "w100": 22.015361083856956,
        "w200": 47.86752185333856,
        "status": "—"
      }
    ],
    "portfolio": [
      {
        "ticker": "VOO",
        "name": "S&P 500 Endeks fonu",
        "group": "portfolio",
        "d50": -0.35061944723246974,
        "d200": 6.428099210715432,
        "w50": 7.357689488173924,
        "w100": 16.179606638781507,
        "w200": 35.91767458880846,
        "status": "—"
      },
      {
        "ticker": "SCHD",
        "name": "US Dividend Equity ETF",
        "group": "portfolio",
        "d50": 1.5932301527326276,
        "d200": 9.543679385116866,
        "w50": 10.395739428833295,
        "w100": 14.680104077864598,
        "w200": 22.286819834122305,
        "status": "Güçlü"
      },
      {
        "ticker": "JEPQ",
        "name": "JPMorgan Nasdaq Equity Premium Income ETF",
        "group": "portfolio",
        "d50": -2.382213545705403,
        "d200": 0.14580055716146845,
        "w50": 0.8430268112284311,
        "w100": 4.144910644423305,
        "w200": 12.210156223439927,
        "status": "—"
      },
      {
        "ticker": "ASTS",
        "name": "AST SpaceMobile",
        "group": "portfolio",
        "d50": -32.67122621343269,
        "d200": -31.041814696158443,
        "w50": -25.489053175883637,
        "w100": 7.853363692789106,
        "w200": 93.40365640984099,
        "status": "—"
      },
      {
        "ticker": "MSFT",
        "name": "Microsoft",
        "group": "portfolio",
        "d50": 0.2521469940448329,
        "d200": -8.314201042484182,
        "w50": -9.984312466218348,
        "w100": -8.625588538502182,
        "w200": 3.157764758800563,
        "status": "—"
      },
      {
        "ticker": "SPGI",
        "name": "S&P Global",
        "group": "portfolio",
        "d50": 10.633460219557733,
        "d200": 2.786145081434621,
        "w50": 0.38633897964355235,
        "w100": -3.453191342810935,
        "w200": 7.211246295311624,
        "status": "Güçlü"
      },
      {
        "ticker": "AVGO",
        "name": "Broadcom Inc.",
        "group": "portfolio",
        "d50": -5.930066696214142,
        "d200": 3.9279560604483788,
        "w50": 5.856660184918905,
        "w100": 33.07639714670809,
        "w200": 99.3106318098666,
        "status": "—"
      },
      {
        "ticker": "BTC-USD",
        "name": "Bitcoin",
        "group": "portfolio",
        "d50": 3.805900667017692,
        "d200": -10.047294714598909,
        "w50": -23.208606666255406,
        "w100": -25.89008295762373,
        "w200": 3.5893033952773434,
        "status": "—"
      },
      {
        "ticker": "ETH-USD",
        "name": "Ethereum",
        "group": "portfolio",
        "d50": 10.618115287234154,
        "d200": -11.99853165592616,
        "w50": -32.060190339989035,
        "w100": -30.958514848522732,
        "w200": -22.662745739695122,
        "status": "—"
      },
      {
        "ticker": "SOL-USD",
        "name": "Solana",
        "group": "portfolio",
        "d50": 6.697044212525394,
        "d200": -12.987005911791826,
        "w50": -37.42004370543126,
        "w100": -47.227272240656184,
        "w200": -27.481132147402377,
        "status": "—"
      },
      {
        "ticker": "AVAX-USD",
        "name": "Avax",
        "group": "portfolio",
        "d50": -1.434748507488015,
        "d200": -28.04655734229219,
        "w50": -51.763741913729625,
        "w100": -67.38223475358592,
        "w200": -69.21431674618215,
        "status": "—"
      },
      {
        "ticker": "HYPE-USD",
        "name": "Hyperliquid",
        "group": "portfolio",
        "d50": -4.0296395734623065,
        "d200": 42.60403134563355,
        "w50": 46.075164520670974,
        "w100": null,
        "w200": null,
        "status": "—"
      },
      {
        "ticker": "GARAN.IS",
        "name": "Garanti BBVA",
        "group": "portfolio",
        "d50": -4.0861684996542635,
        "d200": -8.195437353399749,
        "w50": -8.738896129064578,
        "w100": -2.303719274510818,
        "w200": 39.01116021737505,
        "status": "—"
      },
      {
        "ticker": "FROTO.IS",
        "name": "Ford Otosan",
        "group": "portfolio",
        "d50": -4.076739889677383,
        "d200": -15.290519047399654,
        "w50": -16.41337543682624,
        "w100": -13.933773990295462,
        "w200": -4.204134089975719,
        "status": "—"
      },
      {
        "ticker": "THYAO.IS",
        "name": "THY",
        "group": "portfolio",
        "d50": 4.922939752897704,
        "d200": 9.767015761310894,
        "w50": 8.039871466981442,
        "w100": 9.959787088485106,
        "w200": 28.65452551357115,
        "status": "Güçlü"
      },
      {
        "ticker": "PETKM.IS",
        "name": "Petkim Petrokimya Holding",
        "group": "portfolio",
        "d50": -2.011247350074874,
        "d200": 8.677885272768805,
        "w50": 9.408964825213207,
        "w100": 11.889459873939767,
        "w200": 12.121912643508237,
        "status": "—"
      },
      {
        "ticker": "ISCTR.IS",
        "name": "İş Bankası",
        "group": "portfolio",
        "d50": -3.1079110273876664,
        "d200": -3.374474987942455,
        "w50": -3.7067251832877846,
        "w100": 0.4899646218022635,
        "w200": 24.63489027066579,
        "status": "—"
      }
    ]
  },
  "companyCards": [
    {
      "ticker": "MSFT",
      "name": "Microsoft",
      "currentPrice": 402.29,
      "marketCap": 2988383104700,
      "oneLiner": "Microsoft Corporation is a prominent global technology firm that invents, markets, and provides ongoing assistance for a diverse range of…",
      "logoUrl": "https://images.financialmodelingprep.com/symbol/MSFT.png",
      "revenueGrowthYoY": 0.1493215623240672,
      "netMargin": 0.39342325613545603,
      "fcfGrowthYoY": -0.0332113782721983,
      "peTTM": 23.974373,
      "debtToEquity": 0.30271000000000003,
      "currentRatio": 1.2829483173692569,
      "interestCoverage": null,
      "netDebt": 47203999744,
      "targetPrice": {
        "confidence": "yüksek",
        "bear": 400,
        "base": 561,
        "bull": 680,
        "expected": 550.5,
        "upsidePct": 36.8
      },
      "targetPriceSource": "ai",
      "guidance": [
        "Azure %40 büyüdü; AI iş kolunun yıllık geliri $37 milyarı aştı.",
        "Q4 gelir rehberi $86.7–87.8 milyar; Azure büyümesi %39–40 öngörülüyor.",
        "Yıllık sermaye harcaması $190 milyara çıktı; brüt marjda daralma baskısı oluştu."
      ]
    },
    {
      "ticker": "AVGO",
      "name": "Broadcom Inc.",
      "currentPrice": 378.16,
      "marketCap": 1799126515712,
      "oneLiner": "Broadcom Inc. is a prominent global technology enterprise focused on the innovation, development, and supply of advanced semiconductor…",
      "logoUrl": "https://images.financialmodelingprep.com/symbol/AVGO.png",
      "revenueGrowthYoY": 0.479,
      "netMargin": 0.38848,
      "fcfGrowthYoY": null,
      "peTTM": 62.921795,
      "debtToEquity": 0.7401800000000001,
      "currentRatio": 2.238,
      "interestCoverage": null,
      "netDebt": 45279002624,
      "targetPrice": null,
      "targetPriceSource": null,
      "guidance": null
    },
    {
      "ticker": "GARAN.IS",
      "name": "Garanti BBVA",
      "currentPrice": 126.8,
      "marketCap": 522060005376,
      "oneLiner": "Turkiye Garanti Bankasi A.S. provides various banking products and services in Turkey. It offers current, savings, time deposit, e-savings,…",
      "peTTM": 4.4282155,
      "netMargin": 0.32486,
      "revenueGrowthYoY": 0.497,
      "netDebt": -52734132224,
      "targetPrice": {
        "confidence": "orta",
        "bear": 160.0,
        "base": 185.23,
        "bull": 205.73,
        "expected": 184.05,
        "upsidePct": 45.1
      },
      "targetPriceSource": "ai",
      "guidance": [
        "Q1 2026'da net kâr 33,6 milyar TL; özkaynak getirisi ~%30 korundu.",
        "Net faiz geliri büyümesi güçlü; TL mevduat maliyetlerindeki düşüş kredi faiz gelirlerindeki gerilemeyi telafi etti.",
        "Yönetim kredi büyümesinde yukarı yönlü bir eğilim öngörüyor; varlık kalitesi stabil seyrediyor."
      ]
    },
    {
      "ticker": "THYAO.IS",
      "name": "THY",
      "currentPrice": 329.5,
      "marketCap": 450108948480,
      "oneLiner": "Türk Hava Yollari Anonim Ortakligi provides air transport and aircraft technical maintenance services in Turkey and internationally. The…",
      "peTTM": 33.401222,
      "netMargin": 0.1266,
      "revenueGrowthYoY": 0.211,
      "debtToEquity": 0.83896,
      "currentRatio": 0.976,
      "netDebt": 11912999936,
      "targetPrice": {
        "confidence": "yüksek",
        "bear": 320,
        "base": 442,
        "bull": 650,
        "expected": 463.5,
        "upsidePct": 40.7
      },
      "targetPriceSource": "ai",
      "guidance": [
        "2026 planı: ASK %7-9, gelir %6-9 büyüme, EBITDAR marjı %22-24 hedefleniyor.",
        "Q1 2026'da rekor 4,9 milyar dolar hasılat; enflasyon ve kur baskısı nedeniyle net zarar 44 milyon dolar.",
        "Orta Doğu riskleri ve GTF motor sorunları (~50 uçak yerde) kısa vadeli maliyet baskısı yaratıyor."
      ]
    },
    {
      "ticker": "ISCTR.IS",
      "name": "İş Bankası",
      "currentPrice": 13.68,
      "marketCap": 329500000256,
      "oneLiner": "Türkiye Is Bankasi A.S., together with its subsidiaries, provides various banking products and services to individuals and businesses in…",
      "peTTM": 4.3213115,
      "netMargin": 0.19059,
      "revenueGrowthYoY": 0.62,
      "netDebt": 177432821760,
      "targetPrice": {
        "confidence": "yüksek",
        "bear": 13.5,
        "base": 19.88,
        "bull": 24.46,
        "expected": 19.43,
        "upsidePct": 42.0
      },
      "targetPriceSource": "ai",
      "guidance": [
        "Q1 2026'da net kâr yıllık %68 artışla 20,5 milyar TL'ye ulaştı.",
        "Net faiz marjı toparlanmaya devam ediyor; uzun vadeli hedef yaklaşık %4 seviyesi.",
        "2026'da kredi büyümesi normalleşirken kârlılığın reel bazda korunması hedefleniyor."
      ]
    },
    {
      "ticker": "FROTO.IS",
      "name": "Ford Otosan",
      "currentPrice": 83.6,
      "marketCap": 290027110400,
      "oneLiner": "Ford Otomotiv Sanayi A.S., together with its subsidiaries, engages in the manufacturing, assembly, production, import, and sale of motor…",
      "peTTM": 9.349547,
      "netMargin": 0.03814,
      "revenueGrowthYoY": -0.086,
      "debtToEquity": 1.00153,
      "currentRatio": 1.258,
      "netDebt": 108000129024,
      "targetPrice": {
        "confidence": "yüksek",
        "bear": 120.0,
        "base": 145.45,
        "bull": 227.0,
        "expected": 159.47,
        "upsidePct": 90.8
      },
      "targetPriceSource": "ai",
      "guidance": [
        "Ç1 2026'da net kâr %35 düşerek 5.5 milyar TL'ye geriledi; gelirler yıllık bazda %9 azaldı.",
        "2026 yılı gelir büyüme beklentisi 'yüksek tek haneli'den 'yatay' seviyeye indirildi.",
        "İhracat hacmi güçlü seyrederken yurt içi satışlar ve FAVÖK marjı baskı altında kalmaya devam etti."
      ]
    },
    {
      "ticker": "SPGI",
      "name": "S&P Global",
      "currentPrice": 448.35,
      "marketCap": 132711604224,
      "oneLiner": "S&P Global Inc., together with its subsidiaries, provides benchmarks, data, analytics, and workflow solutions in the global capital, energy…",
      "logoUrl": "https://images.financialmodelingprep.com/symbol/SPGI.png",
      "revenueGrowthYoY": 0.104,
      "netMargin": 0.30361998,
      "fcfGrowthYoY": null,
      "peTTM": 28.34071,
      "debtToEquity": 0.38392000000000004,
      "currentRatio": 0.677,
      "interestCoverage": null,
      "netDebt": 12090000256,
      "targetPrice": {
        "confidence": "yüksek",
        "bear": 480,
        "base": 532,
        "bull": 575,
        "expected": 529.75,
        "upsidePct": 18.2
      },
      "targetPriceSource": "ai",
      "guidance": [
        "2026 tam yıl düzeltilmiş EPS rehberi 19,40-19,65 dolar aralığında korundu.",
        "Gelir büyümesi %6-8 organik sabit kur bazında öngörülüyor; enerji segmenti jeopolitik riskler nedeniyle 1 puan aşağı revize edildi.",
        "Mobility bölümü ayrıştırması ve hisse geri alımları ile hissedar değeri artırımı hedefleniyor."
      ]
    },
    {
      "ticker": "PETKM.IS",
      "name": "Petkim Petrokimya Holding",
      "currentPrice": 20.94,
      "marketCap": 57530880000,
      "oneLiner": "Petkim Petrokimya Holding Anonim Sirketi operates as a petrochemical company in Turkey. It operates through the Petrochemical and Port…",
      "netMargin": -0.070539996,
      "revenueGrowthYoY": 0.167,
      "debtToEquity": 0.76699,
      "currentRatio": 0.555,
      "netDebt": 47111014912,
      "targetPrice": {
        "confidence": "yüksek",
        "bear": 12.0,
        "base": 18.0,
        "bull": 25.0,
        "expected": 18.25,
        "upsidePct": -12.8
      },
      "targetPriceSource": "ai",
      "guidance": [
        "2025 yılını 10,2 milyar TL net zarar ve negatif FAVÖK ile kapattı.",
        "4Ç25 net zararı (5,25 milyar TL) piyasa beklentilerinin belirgin üzerinde gerçekleşti.",
        "Petlim liman hissesi satıldı; yeni etilen/polietilen tesisi için FEED aşamasına geçildi."
      ]
    },
    {
      "ticker": "ASTS",
      "name": "AST SpaceMobile",
      "currentPrice": 57.42,
      "marketCap": 22286112768,
      "oneLiner": "AST SpaceMobile, Inc. establishes and operates a satellite-based cellular broadband network designed to connect directly with standard…",
      "logoUrl": "https://images.financialmodelingprep.com/symbol/ASTS.png",
      "revenueGrowthYoY": 19.522,
      "netMargin": 0.0,
      "fcfGrowthYoY": null,
      "peTTM": null,
      "debtToEquity": 1.1242400000000001,
      "currentRatio": 18.469,
      "interestCoverage": null,
      "netDebt": -38182912,
      "targetPrice": null,
      "targetPriceSource": null,
      "guidance": null
    }
  ]
}